MANIFEST.in
README.txt
setup.py
jbrela_jakubBrela.egg-info/PKG-INFO
jbrela_jakubBrela.egg-info/SOURCES.txt
jbrela_jakubBrela.egg-info/dependency_links.txt
jbrela_jakubBrela.egg-info/requires.txt
jbrela_jakubBrela.egg-info/top_level.txt
myPackage/__init__.py
myPackage/somePython.py
myPackage/packageData/sampleData.dat