Metadata-Version: 1.0
Name: jbrela-jakubBrela
Version: 0.4
Summary: An example python package
Home-page: https://pypi.org/manage/projects/
Author: Jakub Brela
Author-email: UNKNOWN
License: MIT
Platform: UNKNOWN
